netbench/__init__.py
netbench/bandwidth/__init__.py
netbench/bandwidth/command.py
netbench/config.py
netbench/latency/__init__.py
netbench/latency/command.py
netbench/main.py
netbench/ptp/__init__.py
netbench/ptp/command.py
netbench/types.py
netbench/utils.py
netbench-0.1.0.dist-info/entry_points.txt
netbench-0.1.0.dist-info/LICENSE
netbench-0.1.0.dist-info/WHEEL
netbench-0.1.0.dist-info/METADATA
netbench-0.1.0.dist-info/RECORD
