Metadata-Version: 2.1
Name: netbench
Version: 0.1.0
Summary: A complete CLI suite for network benchmarking.
Home-page: https://github.com/rabbits-ugr/netbench
License: MIT
Keywords: benchmarking,synchronization,timing,bandwidth
Author: Víctor Vázquez
Author-email: victorvazrod@ugr.es
Requires-Python: >=3.9,<4.0
Classifier: License :: OSI Approved :: MIT License
Classifier: Programming Language :: Python :: 3
Classifier: Programming Language :: Python :: 3.9
Requires-Dist: click (>=8.0.1,<9.0.0)
Requires-Dist: pandas (>=1.2.5,<2.0.0)
Project-URL: Repository, https://github.com/rabbits-ugr/netbench
